{
  "title": "Cassiopeia · J0139+5621",
  "theme": "光與回歸",
  "lines": [
    "sgrãll sghogd.",
    "snrɛkr shmɔlp.",
    "slrɔnn smrãbg.",
    "snrybm sjrimn.",
    "shhepr shmɔlp.",
    "sŋrins sjratj.",
    "shrahm strens.",
    "shrɛll swrolŋ.",
    "sbrøts sŋriwm.",
    "sdryjt swrugw."
  ],
  "literal": [
    "中子星 · 起源",
    "重 · 別人",
    "附近 · 自己",
    "終結 · 重複",
    "往返 · 別人",
    "光芒 · 黑暗",
    "回聲 · 未來",
    "停留 · 再現",
    "燦爛 · 天頂",
    "星團 · 轉動"
  ],
  "polished": [
    "中子星之後,總是起源。",
    "別人如此重。",
    "附近等待自己。",
    "終結重複得緩慢。",
    "別人往返。",
    "光芒藏著黑暗。",
    "回聲,或說,未來。",
    "停留,然後再現。",
    "燦爛且天頂。",
    "星團還會轉動嗎。"
  ],
  "translation": [
    "中子星之後,總是起源。",
    "別人如此重。",
    "附近等待自己。",
    "終結重複得緩慢。",
    "別人往返。",
    "光芒藏著黑暗。",
    "回聲,或說,未來。",
    "停留,然後再現。",
    "燦爛且天頂。",
    "星團還會轉動嗎。"
  ],
  "_provider": "static",
  "jname": "J0139+5621",
  "constellation": "Cassiopeia"
}